OneGuild/__init__.py
OneGuild/__main__.py
OneGuild/message.py
OneGuild-0.1.dist-info/LICENSE
OneGuild-0.1.dist-info/METADATA
OneGuild-0.1.dist-info/WHEEL
OneGuild-0.1.dist-info/top_level.txt
OneGuild-0.1.dist-info/RECORD
